README.rst
setup.py
dbutils/__init__.py
dbutils/const.py
dbutils/dbutils.py
sqloperate.egg-info/PKG-INFO
sqloperate.egg-info/SOURCES.txt
sqloperate.egg-info/dependency_links.txt
sqloperate.egg-info/not-zip-safe
sqloperate.egg-info/requires.txt
sqloperate.egg-info/top_level.txt